excalidraw_mcp_server/__init__.py
excalidraw_mcp_server/__main__.py
excalidraw_mcp_server/server.py
excalidraw_mcp_server-1.0.3.dist-info/METADATA
excalidraw_mcp_server-1.0.3.dist-info/WHEEL
excalidraw_mcp_server-1.0.3.dist-info/entry_points.txt
excalidraw_mcp_server-1.0.3.dist-info/top_level.txt
excalidraw_mcp_server-1.0.3.dist-info/RECORD
