Metadata-Version: 2.4
Name: excalidraw-mcp-server
Version: 1.0.3
Summary: Excalidraw MCP Server - A Model Context Protocol server for Excalidraw canvas operations
Author-email: Your Name <your.email@example.com>
Project-URL: Homepage, https://github.com/yourusername/excalidraw-mcp-server
Project-URL: Repository, https://github.com/yourusername/excalidraw-mcp-server
Project-URL: Issues, https://github.com/yourusername/excalidraw-mcp-server/issues
Classifier: Development Status :: 4 - Beta
Classifier: Intended Audience :: Developers
Classifier: License :: OSI Approved :: MIT License
Classifier: Programming Language :: Python :: 3
Classifier: Programming Language :: Python :: 3.9
Classifier: Programming Language :: Python :: 3.10
Classifier: Programming Language :: Python :: 3.11
Classifier: Programming Language :: Python :: 3.12
Requires-Python: >=3.9
Requires-Dist: httpx
Requires-Dist: typing-extensions
